{"version":1,"resource":"vscode-remote://ssh-remote%2B502_team2@203.249.87.58:20022/var/www/html/2_team/2_team2/login.php","entries":[{"id":"wh3T.php","timestamp":1732069395137},{"id":"YeSU.php","timestamp":1732069585743},{"id":"HjFT.php","timestamp":1732069762079},{"id":"0vY4.php","timestamp":1732069776514},{"id":"Qcl7.php","timestamp":1732069854937},{"id":"QvoO.php","timestamp":1732069874727},{"id":"uyU5.php","timestamp":1732069903208},{"id":"eTB6.php","timestamp":1732069924277},{"id":"1Beg.php","timestamp":1732070012557},{"id":"0XBt.php","timestamp":1732070036360},{"id":"72Dv.php","timestamp":1732070089922},{"id":"w5i1.php","timestamp":1732070121062},{"id":"8FGb.php","timestamp":1732070157435},{"id":"Gvw0.php","timestamp":1732070174682},{"id":"4fx7.php","timestamp":1732070202163},{"id":"2GDn.php","timestamp":1732078200924},{"id":"4IK6.php","timestamp":1732078316721},{"id":"ENoa.php","timestamp":1732078396927},{"id":"Ugar.php","timestamp":1732083077334},{"id":"k3BK.php","timestamp":1732084998043},{"id":"r1hK.php","timestamp":1732085118549},{"id":"s8ZK.php","timestamp":1732085691593},{"id":"0kB6.php","timestamp":1732086613512},{"id":"imhU.php","timestamp":1732086746364},{"id":"tIIw.php","timestamp":1732117700811},{"id":"8tFY.php","timestamp":1732117907832},{"id":"JQmX.php","timestamp":1732157385424},{"id":"TR5H.php","timestamp":1732161601200},{"id":"iunY.php","timestamp":1732161995736},{"id":"ZacA.php","timestamp":1732162359962},{"id":"usWj.php","timestamp":1732162411949},{"id":"UDXC.php","timestamp":1732162428825},{"id":"Kvuw.php","timestamp":1732162850789},{"id":"BFvi.php","source":"undoRedo.source","timestamp":1732162909373},{"id":"Jr1n.php","timestamp":1732163050223},{"id":"qlVb.php","timestamp":1732166213545},{"id":"3gQ9.php","timestamp":1732166240542},{"id":"xSIQ.php","timestamp":1732168467643},{"id":"iW8N.php","timestamp":1732168521618},{"id":"sD0R.php","timestamp":1732176344625},{"id":"syx1.php","timestamp":1732176544788},{"id":"Vdcc.php","timestamp":1732176572973},{"id":"B4RG.php","timestamp":1732176640196},{"id":"Y035.php","timestamp":1732182353240},{"id":"mwu8.php","timestamp":1732182373335},{"id":"oQmN.php","timestamp":1732182991061},{"id":"GEOq.php","timestamp":1732183124904},{"id":"uyps.php","source":"undoRedo.source","timestamp":1732183141375},{"id":"4F4O.php","timestamp":1732187532148},{"id":"qJ3q.php","timestamp":1732187608559}]}